referral_candy/__init__.py
referral_candy/referral_candy.py
referral_candy-0.3.0.dist-info/LICENSE
referral_candy-0.3.0.dist-info/METADATA
referral_candy-0.3.0.dist-info/WHEEL
referral_candy-0.3.0.dist-info/top_level.txt
referral_candy-0.3.0.dist-info/RECORD
