Metadata-Version: 2.1
Name: referral_candy
Version: 0.3.0
Summary: ReferralCandy Python API Client
Home-page: https://github.com/ReferralCandy/referral_candy_python
Author: ReferralCandy
Author-email: hello@referralcandy.com
License: MIT License
License-File: LICENSE
Requires-Dist: requests
